{
    "dummy": {},
    "random_forest": {},
    "decision_tree": {},
    "xgb": {
        "verbosity": 1,
        "validate_parameters": false,
        "tree_method": "auto",
        "subsample": 1.0,
        "scale_pos_weight": 10,
        "sampling_method": "uniform",
        "process_type": "default",
        "objective": "binary:logistic",
        "num_parallel_tree": 5,
        "nthread": null,
        "min_child_weight": 1,
        "max_leaves": 8,
        "max_depth": 3,
        "max_delta_step": 5,
        "max_bin": 64,
        "lambda": 5,
        "grow_policy": "depthwise",
        "gamma": 5,
        "eta": 0.5,
        "disable_default_eval_metric": false,
        "device": "cpu",
        "colsample_bytree": 0,
        "colsample_bynode": 1.0,
        "colsample_bylevel": 1.0,
        "booster": "gbtree",
        "alpha": 5
    },
    "logistic_regression": {},
    "mord_logisticat": {}
}